divr_benchmark/__init__.py
divr_benchmark/__main__.py
divr_benchmark/convert.py
divr_benchmark/data_counter.py
divr_benchmark/download.py
divr_benchmark/logger.py
divr_benchmark/benchmark/__init__.py
divr_benchmark/benchmark/audio_loader.py
divr_benchmark/benchmark/benchmark.py
divr_benchmark/benchmark/result.py
divr_benchmark/benchmark/task.py
divr_benchmark/prepare_dataset/__init__.py
divr_benchmark/prepare_dataset/database_generator.py
divr_benchmark/prepare_dataset/database_plan.py
divr_benchmark/prepare_dataset/processed.py
divr_benchmark/task_generator/GeneratorV1.py
divr_benchmark/task_generator/__init__.py
divr_benchmark/task_generator/generator.py
divr_benchmark/task_generator/task.py
divr_benchmark/task_generator/databases/Base.py
divr_benchmark/task_generator/databases/__init__.py
divr_benchmark/task_generator/databases/avfad.py
divr_benchmark/task_generator/databases/gender.py
divr_benchmark/task_generator/databases/meei.py
divr_benchmark/task_generator/databases/svd.py
divr_benchmark/task_generator/databases/uaspeech.py
divr_benchmark/task_generator/databases/uncommon_voice.py
divr_benchmark/task_generator/databases/voiced.py
divr_benchmark/task_generator/databases/torgo/__init__.py
divr_benchmark/task_generator/databases/torgo/prompt_stats.py
divr_benchmark/tasks/README.md
divr_benchmark/tasks/Compton_2022-a_n/test.demographics.yml
divr_benchmark/tasks/Compton_2022-a_n/test.yml
divr_benchmark/tasks/Compton_2022-a_n/train.demographics.yml
divr_benchmark/tasks/Compton_2022-a_n/train.yml
divr_benchmark/tasks/Compton_2022-a_n/val.demographics.yml
divr_benchmark/tasks/Compton_2022-a_n/val.yml
divr_benchmark/tasks/Compton_2022-all/test.demographics.yml
divr_benchmark/tasks/Compton_2022-all/test.yml
divr_benchmark/tasks/Compton_2022-all/train.demographics.yml
divr_benchmark/tasks/Compton_2022-all/train.yml
divr_benchmark/tasks/Compton_2022-all/val.demographics.yml
divr_benchmark/tasks/Compton_2022-all/val.yml
divr_benchmark-0.1.4.dist-info/METADATA
divr_benchmark-0.1.4.dist-info/WHEEL
divr_benchmark-0.1.4.dist-info/top_level.txt
divr_benchmark-0.1.4.dist-info/RECORD
