Metadata-Version: 2.2
Name: divr-benchmark
Version: 0.1.4
Summary: Toolkit to work with disordered voice databases
Home-page: https://github.com/ComputationalAudioResearchLab/divr-benchmark
Author: Computational Audio Research Lab
License: MIT
Keywords: ML Audio Features,ML,Disordered Voice Features,Research
Classifier: Development Status :: 4 - Beta
Classifier: Intended Audience :: Science/Research
Classifier: License :: OSI Approved :: MIT License
Classifier: Operating System :: OS Independent
Classifier: Topic :: Scientific/Engineering
Requires-Dist: aiofiles>=23.1.0
Requires-Dist: aiohttp>=3.8.4
Requires-Dist: class-argparse>=0.1.3
Requires-Dist: divr-diagnosis>=0.1.2
Requires-Dist: librosa>=0.10.0.post2
Requires-Dist: matplotlib>=3.7.1
Requires-Dist: nspfile>=0.1.4
Requires-Dist: openpyxl>=3.1.2
Requires-Dist: pandas>=2.0.1
Requires-Dist: PyYAML>=6.0.1
Requires-Dist: svd-downloader>=0.1.1
Requires-Dist: wfdb>=4.1.2
Requires-Dist: xlrd>=2.0.1
Dynamic: author
Dynamic: classifier
Dynamic: description
Dynamic: description-content-type
Dynamic: home-page
Dynamic: keywords
Dynamic: license
Dynamic: requires-dist
Dynamic: summary
